{"id":8412629,"docketId":65608314,"caseName":"Tart v. Kornegay","caseNameFull":"Larry R. TART v. Joyce KORNEGAY","slug":"tart-v-kornegay","docketNumber":"13-5949","dateFiled":"2013-10-21","dateArgued":null,"dateCertGranted":null,"year":2013,"scdbId":"","direction":"","votesMajority":null,"votesMinority":null,"disposition":"","posture":"","syllabus":null,"summary":null,"headnotes":null,"proceduralHistory":null,"attorneys":null,"natureOfSuit":"","citationCount":0,"judges":"","jurisdictionType":"","opinions":[{"id":8382973,"type":"majority","typeCode":"020lead","perCuriam":false,"author":"","joinedBy":"","pageCount":null,"textLength":0,"text":null}],"citations":[]}