{"id":8413091,"docketId":65608783,"caseName":"Diaz v. Crews","caseNameFull":"Angel DIAZ v. Michael D. CREWS, Secretary, Florida Department of Corrections.","slug":"diaz-v-crews","docketNumber":"13-6557","dateFiled":"2013-11-12","dateArgued":null,"dateCertGranted":null,"year":2013,"scdbId":"","direction":"","votesMajority":null,"votesMinority":null,"disposition":"","posture":"","syllabus":null,"summary":null,"headnotes":null,"proceduralHistory":null,"attorneys":null,"natureOfSuit":"","citationCount":0,"judges":"","jurisdictionType":"","opinions":[{"id":8383435,"type":"majority","typeCode":"020lead","perCuriam":false,"author":"","joinedBy":"","pageCount":null,"textLength":0,"text":null}],"citations":[]}