{"id":8414426,"docketId":65610191,"caseName":"Brown v. United States","caseNameFull":"Reginald BROWN v. UNITED STATES.","slug":"brown-v-united-states","docketNumber":"13-7462","dateFiled":"2014-01-13","dateArgued":null,"dateCertGranted":null,"year":2014,"scdbId":"","direction":"","votesMajority":null,"votesMinority":null,"disposition":"","posture":"","syllabus":null,"summary":null,"headnotes":null,"proceduralHistory":null,"attorneys":null,"natureOfSuit":"","citationCount":0,"judges":"","jurisdictionType":"","opinions":[{"id":8384770,"type":"majority","typeCode":"020lead","perCuriam":false,"author":"","joinedBy":"","pageCount":null,"textLength":0,"text":null}],"citations":[]}