{"id":8414727,"docketId":65610504,"caseName":"Noshafagh v. Leggett","caseNameFull":"Sara NOSHAFAGH v. Isiah LEGGETT, County Executive, Montgomery County, Maryland","slug":"noshafagh-v-leggett","docketNumber":"13-594","dateFiled":"2014-01-21","dateArgued":null,"dateCertGranted":null,"year":2014,"scdbId":"","direction":"","votesMajority":null,"votesMinority":null,"disposition":"","posture":"","syllabus":null,"summary":null,"headnotes":null,"proceduralHistory":null,"attorneys":null,"natureOfSuit":"","citationCount":0,"judges":"","jurisdictionType":"","opinions":[{"id":8385071,"type":"majority","typeCode":"020lead","perCuriam":false,"author":"","joinedBy":"","pageCount":null,"textLength":0,"text":null}],"citations":[]}