{"id":8415933,"docketId":65611787,"caseName":"Hatch v. United States","caseNameFull":"William HATCH v. UNITED STATES.","slug":"hatch-v-united-states","docketNumber":"13-6765","dateFiled":"2014-03-24","dateArgued":null,"dateCertGranted":null,"year":2014,"scdbId":"","direction":"","votesMajority":null,"votesMinority":null,"disposition":"","posture":"","syllabus":null,"summary":null,"headnotes":null,"proceduralHistory":null,"attorneys":null,"natureOfSuit":"","citationCount":1,"judges":"","jurisdictionType":"","opinions":[{"id":8386277,"type":"majority","typeCode":"020lead","perCuriam":false,"author":"","joinedBy":"","pageCount":null,"textLength":0,"text":null}],"citations":[]}