{"id":8415076,"docketId":65610899,"caseName":"Fernandez-Rubio v. United States","caseNameFull":"Jose FERNANDEZ-RUBIO v. UNITED STATES Juan Ivan Flores-Perla v. United States Jose Luis Lopez-Bernal v. United States Victor Manuel Alcaraz-Jimenez v. United States and Paulo Santibanez-Luviano v. United States.","slug":"fernandez-rubio-v-united-states","docketNumber":"13-6852","dateFiled":"2014-02-24","dateArgued":null,"dateCertGranted":null,"year":2014,"scdbId":"","direction":"","votesMajority":null,"votesMinority":null,"disposition":"","posture":"","syllabus":null,"summary":null,"headnotes":null,"proceduralHistory":null,"attorneys":null,"natureOfSuit":"","citationCount":0,"judges":"","jurisdictionType":"","opinions":[{"id":8385420,"type":"majority","typeCode":"020lead","perCuriam":false,"author":"","joinedBy":"","pageCount":null,"textLength":0,"text":null}],"citations":[]}