{"id":8416656,"docketId":65612515,"caseName":"Vincent v. United States","caseNameFull":"Veronica VINCENT v. UNITED STATES","slug":"vincent-v-united-states","docketNumber":"13-8937","dateFiled":"2014-04-21","dateArgued":null,"dateCertGranted":null,"year":2014,"scdbId":"","direction":"","votesMajority":null,"votesMinority":null,"disposition":"","posture":"","syllabus":null,"summary":null,"headnotes":null,"proceduralHistory":null,"attorneys":null,"natureOfSuit":"","citationCount":0,"judges":"","jurisdictionType":"","opinions":[{"id":8387000,"type":"majority","typeCode":"020lead","perCuriam":false,"author":"","joinedBy":"","pageCount":null,"textLength":0,"text":null}],"citations":[]}