{"id":8417389,"docketId":65613279,"caseName":"Yan v. Penn State Univ.","caseNameFull":"YAN YAN v. PENN STATE UNIVERSITY","slug":"yan-v-penn-state-univ","docketNumber":"No. 13\u20139451.","dateFiled":"2014-05-19","dateArgued":null,"dateCertGranted":null,"year":2014,"scdbId":"","direction":"","votesMajority":null,"votesMinority":null,"disposition":"","posture":"","syllabus":null,"summary":null,"headnotes":null,"proceduralHistory":null,"attorneys":null,"natureOfSuit":"","citationCount":0,"judges":"","jurisdictionType":"","opinions":[{"id":8387734,"type":"majority","typeCode":"020lead","perCuriam":false,"author":"","joinedBy":"","pageCount":null,"textLength":0,"text":null}],"citations":[]}