{"id":8417882,"docketId":65613883,"caseName":"Sowell v. United States","caseNameFull":"Anthony Walker SOWELL v. UNITED STATES.","slug":"sowell-v-united-states","docketNumber":"13-9991","dateFiled":"2014-06-02","dateArgued":null,"dateCertGranted":null,"year":2014,"scdbId":"","direction":"","votesMajority":null,"votesMinority":null,"disposition":"","posture":"","syllabus":null,"summary":null,"headnotes":null,"proceduralHistory":null,"attorneys":null,"natureOfSuit":"","citationCount":0,"judges":"","jurisdictionType":"","opinions":[{"id":8388227,"type":"majority","typeCode":"020lead","perCuriam":false,"author":"","joinedBy":"","pageCount":null,"textLength":0,"text":null}],"citations":[]}