{"id":8418331,"docketId":65614336,"caseName":"Goodale v. United States","caseNameFull":"Michael GOODALE v. UNITED STATES.","slug":"goodale-v-united-states","docketNumber":"13-10173","dateFiled":"2014-06-23","dateArgued":null,"dateCertGranted":null,"year":2014,"scdbId":"","direction":"","votesMajority":null,"votesMinority":null,"disposition":"","posture":"","syllabus":null,"summary":null,"headnotes":null,"proceduralHistory":null,"attorneys":null,"natureOfSuit":"","citationCount":0,"judges":"","jurisdictionType":"","opinions":[{"id":8388676,"type":"majority","typeCode":"020lead","perCuriam":false,"author":"","joinedBy":"","pageCount":null,"textLength":0,"text":null}],"citations":[]}