{"id":8418991,"docketId":65615065,"caseName":"Wright v. United States","caseNameFull":"Michael WRIGHT v. UNITED STATES.","slug":"wright-v-united-states","docketNumber":"14-9408","dateFiled":"2015-10-05","dateArgued":null,"dateCertGranted":null,"year":2015,"scdbId":"","direction":"","votesMajority":null,"votesMinority":null,"disposition":"","posture":"","syllabus":null,"summary":null,"headnotes":null,"proceduralHistory":null,"attorneys":null,"natureOfSuit":"","citationCount":0,"judges":"","jurisdictionType":"","opinions":[{"id":8389338,"type":"majority","typeCode":"020lead","perCuriam":false,"author":"","joinedBy":"","pageCount":null,"textLength":0,"text":null}],"citations":[]}