{"id":8418375,"docketId":65614380,"caseName":"Rivers v. United States","caseNameFull":"Eric Miguel RIVERS v. UNITED STATES.","slug":"rivers-v-united-states","docketNumber":"13-10293","dateFiled":"2014-06-23","dateArgued":null,"dateCertGranted":null,"year":2014,"scdbId":"","direction":"","votesMajority":null,"votesMinority":null,"disposition":"","posture":"","syllabus":null,"summary":null,"headnotes":null,"proceduralHistory":null,"attorneys":null,"natureOfSuit":"","citationCount":0,"judges":"","jurisdictionType":"","opinions":[{"id":8388720,"type":"majority","typeCode":"020lead","perCuriam":false,"author":"","joinedBy":"","pageCount":null,"textLength":0,"text":null}],"citations":[]}