{"id":8419177,"docketId":65615259,"caseName":"Marcus v. Maryland","caseNameFull":"Aaron Christopher MARCUS v. MARYLAND.","slug":"marcus-v-maryland","docketNumber":"14-9856","dateFiled":"2015-10-05","dateArgued":null,"dateCertGranted":null,"year":2015,"scdbId":"","direction":"","votesMajority":null,"votesMinority":null,"disposition":"","posture":"","syllabus":null,"summary":null,"headnotes":null,"proceduralHistory":null,"attorneys":null,"natureOfSuit":"","citationCount":0,"judges":"","jurisdictionType":"","opinions":[{"id":8389524,"type":"majority","typeCode":"020lead","perCuriam":false,"author":"","joinedBy":"","pageCount":null,"textLength":0,"text":null}],"citations":[]}