{"id":8419156,"docketId":65615238,"caseName":"Kawa Orthodontics, LLP v. Lew","caseNameFull":"KAWA ORTHODONTICS, LLP v. Jacob J. LEW, Secretary of the Treasury","slug":"kawa-orthodontics-llp-v-lew","docketNumber":"14-1367","dateFiled":"2015-10-05","dateArgued":null,"dateCertGranted":null,"year":2015,"scdbId":"","direction":"","votesMajority":null,"votesMinority":null,"disposition":"","posture":"","syllabus":null,"summary":null,"headnotes":null,"proceduralHistory":null,"attorneys":null,"natureOfSuit":"","citationCount":0,"judges":"","jurisdictionType":"","opinions":[{"id":8389503,"type":"majority","typeCode":"020lead","perCuriam":false,"author":"","joinedBy":"","pageCount":null,"textLength":0,"text":null}],"citations":[]}