{"id":8419539,"docketId":65615622,"caseName":"Kornegay v. Old Republic Nat'l Title Ins. Co.","caseNameFull":"Marianne KORNEGAY, et vir v. OLD REPUBLIC NATIONAL TITLE INSURANCE COMPANY","slug":"kornegay-v-old-republic-natl-title-ins-co","docketNumber":"14-1487","dateFiled":"2015-10-05","dateArgued":null,"dateCertGranted":null,"year":2015,"scdbId":"","direction":"","votesMajority":null,"votesMinority":null,"disposition":"","posture":"","syllabus":null,"summary":null,"headnotes":null,"proceduralHistory":null,"attorneys":null,"natureOfSuit":"","citationCount":0,"judges":"","jurisdictionType":"","opinions":[{"id":8389886,"type":"majority","typeCode":"020lead","perCuriam":false,"author":"","joinedBy":"","pageCount":null,"textLength":0,"text":null}],"citations":[]}