{"id":8420148,"docketId":65616232,"caseName":"Ram v. United States","caseNameFull":"Santosh RAM v. UNITED STATES.","slug":"ram-v-united-states","docketNumber":"15-5366","dateFiled":"2015-10-05","dateArgued":null,"dateCertGranted":null,"year":2015,"scdbId":"","direction":"","votesMajority":null,"votesMinority":null,"disposition":"","posture":"","syllabus":null,"summary":null,"headnotes":null,"proceduralHistory":null,"attorneys":null,"natureOfSuit":"","citationCount":0,"judges":"","jurisdictionType":"","opinions":[{"id":8390495,"type":"majority","typeCode":"020lead","perCuriam":false,"author":"","joinedBy":"","pageCount":null,"textLength":0,"text":null}],"citations":[]}