{"id":8421980,"docketId":65618148,"caseName":"Collie v. S.C. Comm'n On Lawyer Conduct","caseNameFull":"Cynthia E. COLLIE v. SOUTH CAROLINA COMMISSION ON LAWYER CONDUCT.","slug":"collie-v-sc-commn-on-lawyer-conduct","docketNumber":"No. 15\u20135767.","dateFiled":"2015-12-07","dateArgued":null,"dateCertGranted":null,"year":2015,"scdbId":"","direction":"","votesMajority":null,"votesMinority":null,"disposition":"","posture":"","syllabus":null,"summary":null,"headnotes":null,"proceduralHistory":null,"attorneys":null,"natureOfSuit":"","citationCount":0,"judges":"","jurisdictionType":"","opinions":[{"id":8392329,"type":"majority","typeCode":"020lead","perCuriam":false,"author":"","joinedBy":"","pageCount":null,"textLength":0,"text":null}],"citations":[]}