{"id":8421231,"docketId":65617393,"caseName":"Ctr. for Competitive Politics v. Harris","caseNameFull":"CENTER FOR COMPETITIVE POLITICS v. Kamala D. HARRIS, Attorney General of California.","slug":"ctr-for-competitive-politics-v-harris","docketNumber":"15-152","dateFiled":"2015-11-09","dateArgued":null,"dateCertGranted":null,"year":2015,"scdbId":"","direction":"","votesMajority":null,"votesMinority":null,"disposition":"","posture":"","syllabus":null,"summary":null,"headnotes":null,"proceduralHistory":null,"attorneys":null,"natureOfSuit":"","citationCount":0,"judges":"","jurisdictionType":"","opinions":[{"id":8391579,"type":"majority","typeCode":"020lead","perCuriam":false,"author":"","joinedBy":"","pageCount":null,"textLength":0,"text":null}],"citations":[]}