{"id":8422163,"docketId":65618331,"caseName":"Commonwealth v. Valle","caseNameFull":"Commonwealth of PUERTO RICO v. Luis M. SANZCHEZ VALLE","slug":"commonwealth-v-valle","docketNumber":"No. 15\u2013108.","dateFiled":"2016-01-08","dateArgued":null,"dateCertGranted":null,"year":2016,"scdbId":"","direction":"","votesMajority":null,"votesMinority":null,"disposition":"","posture":"","syllabus":null,"summary":null,"headnotes":null,"proceduralHistory":null,"attorneys":null,"natureOfSuit":"","citationCount":0,"judges":"","jurisdictionType":"","opinions":[{"id":8392512,"type":"majority","typeCode":"020lead","perCuriam":false,"author":"","joinedBy":"","pageCount":null,"textLength":0,"text":null}],"citations":[]}