{"id":8423261,"docketId":65619443,"caseName":"Petrick v. Thornton","caseNameFull":"Robert James PETRICK v. Cynthia O. THORNTON.","slug":"petrick-v-thornton","docketNumber":"15-7308","dateFiled":"2016-02-29","dateArgued":null,"dateCertGranted":null,"year":2016,"scdbId":"","direction":"","votesMajority":null,"votesMinority":null,"disposition":"","posture":"","syllabus":null,"summary":null,"headnotes":null,"proceduralHistory":null,"attorneys":null,"natureOfSuit":"","citationCount":0,"judges":"","jurisdictionType":"","opinions":[{"id":8393613,"type":"majority","typeCode":"020lead","perCuriam":false,"author":"","joinedBy":"","pageCount":null,"textLength":0,"text":null}],"citations":[]}