{"id":8423439,"docketId":65619622,"caseName":"Friday v. Northcarolina","caseNameFull":"Thomas Clay FRIDAY v. NORTH CAROLINA.","slug":"friday-v-northcarolina","docketNumber":"15-7555","dateFiled":"2016-02-29","dateArgued":null,"dateCertGranted":null,"year":2016,"scdbId":"","direction":"","votesMajority":null,"votesMinority":null,"disposition":"","posture":"","syllabus":null,"summary":null,"headnotes":null,"proceduralHistory":null,"attorneys":null,"natureOfSuit":"","citationCount":0,"judges":"","jurisdictionType":"","opinions":[{"id":8393791,"type":"majority","typeCode":"020lead","perCuriam":false,"author":"","joinedBy":"","pageCount":null,"textLength":0,"text":null}],"citations":[]}