{"id":8424874,"docketId":65621059,"caseName":"Parker v. Minnesota","caseNameFull":"Steven Todd PARKER v. MINNESOTA.","slug":"parker-v-minnesota","docketNumber":"15-8323","dateFiled":"2016-04-25","dateArgued":null,"dateCertGranted":null,"year":2016,"scdbId":"","direction":"","votesMajority":null,"votesMinority":null,"disposition":"","posture":"","syllabus":null,"summary":null,"headnotes":null,"proceduralHistory":null,"attorneys":null,"natureOfSuit":"","citationCount":0,"judges":"","jurisdictionType":"","opinions":[{"id":8395228,"type":"majority","typeCode":"020lead","perCuriam":false,"author":"","joinedBy":"","pageCount":null,"textLength":0,"text":null}],"citations":[]}