{"id":8424501,"docketId":65620686,"caseName":"Fewins v. Carlson","caseNameFull":"Scott FEWINS v. Robert CARLSON, Personal Representative of the Estate of Craig Carlson.","slug":"fewins-v-carlson","docketNumber":"15-850","dateFiled":"2016-04-18","dateArgued":null,"dateCertGranted":null,"year":2016,"scdbId":"","direction":"","votesMajority":null,"votesMinority":null,"disposition":"","posture":"","syllabus":null,"summary":null,"headnotes":null,"proceduralHistory":null,"attorneys":null,"natureOfSuit":"","citationCount":0,"judges":"","jurisdictionType":"","opinions":[{"id":8394855,"type":"majority","typeCode":"020lead","perCuriam":false,"author":"","joinedBy":"","pageCount":null,"textLength":0,"text":null}],"citations":[]}