{"id":8424269,"docketId":65620454,"caseName":"Jimenez-Echevarria v. United States","caseNameFull":"Jose David JIMENEZ-ECHEVARRIA v. UNITED STATES.","slug":"jimenez-echevarria-v-united-states","docketNumber":"15-8298","dateFiled":"2016-03-28","dateArgued":null,"dateCertGranted":null,"year":2016,"scdbId":"","direction":"","votesMajority":null,"votesMinority":null,"disposition":"","posture":"","syllabus":null,"summary":null,"headnotes":null,"proceduralHistory":null,"attorneys":null,"natureOfSuit":"","citationCount":0,"judges":"","jurisdictionType":"","opinions":[{"id":8394623,"type":"majority","typeCode":"020lead","perCuriam":false,"author":"","joinedBy":"","pageCount":null,"textLength":0,"text":null}],"citations":[]}