{"id":8424937,"docketId":65621127,"caseName":"Michigan v. Edwards","caseNameFull":"MICHIGAN v. Sidney Ford EDWARDS, III.","slug":"michigan-v-edwards","docketNumber":"15-948","dateFiled":"2016-04-27","dateArgued":null,"dateCertGranted":null,"year":2016,"scdbId":"","direction":"","votesMajority":null,"votesMinority":null,"disposition":"","posture":"","syllabus":null,"summary":null,"headnotes":null,"proceduralHistory":null,"attorneys":null,"natureOfSuit":"","citationCount":0,"judges":"","jurisdictionType":"","opinions":[{"id":8395291,"type":"majority","typeCode":"020lead","perCuriam":false,"author":"","joinedBy":"","pageCount":null,"textLength":0,"text":null}],"citations":[]}