{"id":8426630,"docketId":65622955,"caseName":"Koller v. Michigan","caseNameFull":"Jerrad KOLLER v. MICHIGAN.","slug":"koller-v-michigan","docketNumber":"15-9340","dateFiled":"2016-10-03","dateArgued":null,"dateCertGranted":null,"year":2016,"scdbId":"","direction":"","votesMajority":null,"votesMinority":null,"disposition":"","posture":"","syllabus":null,"summary":null,"headnotes":null,"proceduralHistory":null,"attorneys":null,"natureOfSuit":"","citationCount":0,"judges":"","jurisdictionType":"","opinions":[{"id":8396986,"type":"majority","typeCode":"020lead","perCuriam":false,"author":"","joinedBy":"","pageCount":null,"textLength":0,"text":null}],"citations":[]}