{"id":8426558,"docketId":65622883,"caseName":"Wright v. Maynard","caseNameFull":"Beverly Dina WRIGHT v. Robert A. MAYNARD.","slug":"wright-v-maynard","docketNumber":"15-9230","dateFiled":"2016-10-03","dateArgued":null,"dateCertGranted":null,"year":2016,"scdbId":"","direction":"","votesMajority":null,"votesMinority":null,"disposition":"","posture":"","syllabus":null,"summary":null,"headnotes":null,"proceduralHistory":null,"attorneys":null,"natureOfSuit":"","citationCount":0,"judges":"","jurisdictionType":"","opinions":[{"id":8396914,"type":"majority","typeCode":"020lead","perCuriam":false,"author":"","joinedBy":"","pageCount":null,"textLength":0,"text":null}],"citations":[]}