{"id":8427634,"docketId":65623990,"caseName":"Batamula v. United States","caseNameFull":"Innocent Rutahagara BATAMULA v. UNITED STATES.","slug":"batamula-v-united-states","docketNumber":"16-161","dateFiled":"2016-10-03","dateArgued":null,"dateCertGranted":null,"year":2016,"scdbId":"","direction":"","votesMajority":null,"votesMinority":null,"disposition":"","posture":"","syllabus":null,"summary":null,"headnotes":null,"proceduralHistory":null,"attorneys":null,"natureOfSuit":"","citationCount":0,"judges":"","jurisdictionType":"","opinions":[{"id":8397990,"type":"majority","typeCode":"020lead","perCuriam":false,"author":"","joinedBy":"","pageCount":null,"textLength":0,"text":null}],"citations":[]}