{"id":8427059,"docketId":65623394,"caseName":"Polanco v. Ducart","caseNameFull":"Ricardo POLANCO v. Clark E. DUCART, Warden.","slug":"polanco-v-ducart","docketNumber":"15-9812","dateFiled":"2016-10-03","dateArgued":null,"dateCertGranted":null,"year":2016,"scdbId":"","direction":"","votesMajority":null,"votesMinority":null,"disposition":"","posture":"","syllabus":null,"summary":null,"headnotes":null,"proceduralHistory":null,"attorneys":null,"natureOfSuit":"","citationCount":0,"judges":"","jurisdictionType":"","opinions":[{"id":8397415,"type":"majority","typeCode":"020lead","perCuriam":false,"author":"","joinedBy":"","pageCount":null,"textLength":0,"text":null}],"citations":[]}