{"id":8428065,"docketId":65624437,"caseName":"Saxon v. Smith","caseNameFull":"Jean SAXON v. Robert SMITH, Superintendent, State Correctional Institution at Muncy","slug":"saxon-v-smith","docketNumber":"16-5640","dateFiled":"2016-10-11","dateArgued":null,"dateCertGranted":null,"year":2016,"scdbId":"","direction":"","votesMajority":null,"votesMinority":null,"disposition":"","posture":"","syllabus":null,"summary":null,"headnotes":null,"proceduralHistory":null,"attorneys":null,"natureOfSuit":"","citationCount":0,"judges":"","jurisdictionType":"","opinions":[{"id":8398421,"type":"majority","typeCode":"020lead","perCuriam":false,"author":"","joinedBy":"","pageCount":null,"textLength":0,"text":null}],"citations":[]}