{"id":8429374,"docketId":65625778,"caseName":"Scaggs v. United States","caseNameFull":"David SCAGGS v. UNITED STATES.","slug":"scaggs-v-united-states","docketNumber":"16-6665","dateFiled":"2016-12-12","dateArgued":null,"dateCertGranted":null,"year":2016,"scdbId":"","direction":"","votesMajority":null,"votesMinority":null,"disposition":"","posture":"","syllabus":null,"summary":null,"headnotes":null,"proceduralHistory":null,"attorneys":null,"natureOfSuit":"","citationCount":0,"judges":"","jurisdictionType":"","opinions":[{"id":8399730,"type":"majority","typeCode":"020lead","perCuriam":false,"author":"","joinedBy":"","pageCount":null,"textLength":0,"text":null}],"citations":[]}