{"id":8430427,"docketId":65626890,"caseName":"Cohan v. United States","caseNameFull":"Gregory P. COHAN v. UNITED STATES.","slug":"cohan-v-united-states","docketNumber":"16-726","dateFiled":"2017-02-21","dateArgued":null,"dateCertGranted":null,"year":2017,"scdbId":"","direction":"","votesMajority":null,"votesMinority":null,"disposition":"","posture":"","syllabus":null,"summary":null,"headnotes":null,"proceduralHistory":null,"attorneys":null,"natureOfSuit":"","citationCount":0,"judges":"","jurisdictionType":"","opinions":[{"id":8400784,"type":"majority","typeCode":"020lead","perCuriam":false,"author":"","joinedBy":"","pageCount":null,"textLength":0,"text":null}],"citations":[]}