{"id":8432601,"docketId":65629072,"caseName":"Conway v. Shuford","caseNameFull":"R.L. Butch CONWAY, Sheriff, Gwinnett County, Georgia v. Justin SHUFORD","slug":"conway-v-shuford","docketNumber":"16-1233","dateFiled":"2017-05-30","dateArgued":null,"dateCertGranted":null,"year":2017,"scdbId":"","direction":"","votesMajority":null,"votesMinority":null,"disposition":"","posture":"","syllabus":null,"summary":null,"headnotes":null,"proceduralHistory":null,"attorneys":null,"natureOfSuit":"","citationCount":0,"judges":"","jurisdictionType":"","opinions":[{"id":8402961,"type":"majority","typeCode":"020lead","perCuriam":false,"author":"","joinedBy":"","pageCount":null,"textLength":0,"text":null}],"citations":[]}