{"id":8432201,"docketId":65628671,"caseName":"McArthur v. Bolden","caseNameFull":"Steven Laron McARTHUR v. Kennie L. BOLDEN","slug":"mcarthur-v-bolden","docketNumber":"16-8224","dateFiled":"2017-05-15","dateArgued":null,"dateCertGranted":null,"year":2017,"scdbId":"","direction":"","votesMajority":null,"votesMinority":null,"disposition":"","posture":"","syllabus":null,"summary":null,"headnotes":null,"proceduralHistory":null,"attorneys":null,"natureOfSuit":"","citationCount":0,"judges":"","jurisdictionType":"","opinions":[{"id":8402559,"type":"majority","typeCode":"020lead","perCuriam":false,"author":"","joinedBy":"","pageCount":null,"textLength":0,"text":null}],"citations":[]}