{"id":8432987,"docketId":65629458,"caseName":"Piper v. United States","caseNameFull":"Frank Sharron PIPER, III v. UNITED STATES.","slug":"piper-v-united-states","docketNumber":"16-7662","dateFiled":"2017-06-19","dateArgued":null,"dateCertGranted":null,"year":2017,"scdbId":"","direction":"","votesMajority":null,"votesMinority":null,"disposition":"","posture":"","syllabus":null,"summary":null,"headnotes":null,"proceduralHistory":null,"attorneys":null,"natureOfSuit":"","citationCount":0,"judges":"","jurisdictionType":"","opinions":[{"id":8403348,"type":"majority","typeCode":"020lead","perCuriam":false,"author":"","joinedBy":"","pageCount":null,"textLength":0,"text":null}],"citations":[]}