{"id":8433279,"docketId":65629750,"caseName":"Gomez-Olivas v. United States","caseNameFull":"Gonzalo GOMEZ-OLIVAS v. UNITED STATES.","slug":"gomez-olivas-v-united-states","docketNumber":"16-9233","dateFiled":"2017-06-26","dateArgued":null,"dateCertGranted":null,"year":2017,"scdbId":"","direction":"","votesMajority":null,"votesMinority":null,"disposition":"","posture":"","syllabus":null,"summary":null,"headnotes":null,"proceduralHistory":null,"attorneys":null,"natureOfSuit":"","citationCount":0,"judges":"","jurisdictionType":"","opinions":[{"id":8403640,"type":"majority","typeCode":"020lead","perCuriam":false,"author":"","joinedBy":"","pageCount":null,"textLength":0,"text":null}],"citations":[]}