{"id":9334917,"docketId":66644782,"caseName":"Smith v. City of L. A.","caseNameFull":"Michael SMITH v. CITY OF LOS ANGELES, CALIFORNIA","slug":"smith-v-city-of-l-a","docketNumber":"17-308","dateFiled":"2017-10-30","dateArgued":null,"dateCertGranted":null,"year":2017,"scdbId":"","direction":"","votesMajority":null,"votesMinority":null,"disposition":"","posture":"","syllabus":null,"summary":null,"headnotes":null,"proceduralHistory":null,"attorneys":null,"natureOfSuit":"","citationCount":0,"judges":"","jurisdictionType":"","opinions":[{"id":9330255,"type":"majority","typeCode":"020lead","perCuriam":false,"author":"","joinedBy":"","pageCount":null,"textLength":0,"text":null}],"citations":[]}