{"id":9335865,"docketId":66645814,"caseName":"Michigan v. Terrance","caseNameFull":"MICHIGAN v. Treshaun TERRANCE.","slug":"michigan-v-terrance","docketNumber":"17-1097","dateFiled":"2018-03-26","dateArgued":null,"dateCertGranted":null,"year":2018,"scdbId":"","direction":"","votesMajority":null,"votesMinority":null,"disposition":"","posture":"","syllabus":null,"summary":null,"headnotes":null,"proceduralHistory":null,"attorneys":null,"natureOfSuit":"","citationCount":1,"judges":"","jurisdictionType":"","opinions":[{"id":9331203,"type":"majority","typeCode":"020lead","perCuriam":false,"author":"","joinedBy":"","pageCount":null,"textLength":0,"text":null}],"citations":[]}