{"id":9335787,"docketId":66645729,"caseName":"Korzybski v. United States","caseNameFull":"Soren Davis KORZYBSKI v. UNITED STATES.","slug":"korzybski-v-united-states","docketNumber":"No. 17M86.","dateFiled":"2018-02-26","dateArgued":null,"dateCertGranted":null,"year":2018,"scdbId":"","direction":"","votesMajority":null,"votesMinority":null,"disposition":"","posture":"","syllabus":null,"summary":null,"headnotes":null,"proceduralHistory":null,"attorneys":null,"natureOfSuit":"","citationCount":0,"judges":"","jurisdictionType":"","opinions":[{"id":9331125,"type":"majority","typeCode":"020lead","perCuriam":false,"author":"","joinedBy":"","pageCount":null,"textLength":0,"text":null}],"citations":[]}