{"id":9336439,"docketId":66646427,"caseName":"Ziming Shen v. City of N.Y.","caseNameFull":"ZIMING SHEN v. CITY OF NEW YORK, NEW YORK","slug":"ziming-shen-v-city-of-ny","docketNumber":"17-1512","dateFiled":"2018-10-01","dateArgued":null,"dateCertGranted":null,"year":2018,"scdbId":"","direction":"","votesMajority":null,"votesMinority":null,"disposition":"","posture":"","syllabus":null,"summary":null,"headnotes":null,"proceduralHistory":null,"attorneys":null,"natureOfSuit":"","citationCount":0,"judges":"","jurisdictionType":"","opinions":[{"id":9331777,"type":"majority","typeCode":"020lead","perCuriam":false,"author":"","joinedBy":"","pageCount":null,"textLength":0,"text":null}],"citations":[]}