{"id":9336302,"docketId":66646287,"caseName":"Oldham v. United States","caseNameFull":"Jonathan OLDHAM v. UNITED STATES.","slug":"oldham-v-united-states","docketNumber":"17-7703","dateFiled":"2018-10-01","dateArgued":null,"dateCertGranted":null,"year":2018,"scdbId":"","direction":"","votesMajority":null,"votesMinority":null,"disposition":"","posture":"","syllabus":null,"summary":null,"headnotes":null,"proceduralHistory":null,"attorneys":null,"natureOfSuit":"","citationCount":0,"judges":"","jurisdictionType":"","opinions":[{"id":9331640,"type":"majority","typeCode":"020lead","perCuriam":false,"author":"","joinedBy":"","pageCount":null,"textLength":0,"text":null}],"citations":[]}