{"id":9336804,"docketId":66646793,"caseName":"Pierre v. Attorney Grievance Comm. for the First Judicial Dep't","caseNameFull":"Alex H. PIERRE v. ATTORNEY GRIEVANCE COMMITTEE FOR the FIRST JUDICIAL DEPARTMENT.","slug":"pierre-v-attorney-grievance-comm-for-the-first-judicial-dept","docketNumber":"17-9253","dateFiled":"2018-10-01","dateArgued":null,"dateCertGranted":null,"year":2018,"scdbId":"","direction":"","votesMajority":null,"votesMinority":null,"disposition":"","posture":"","syllabus":null,"summary":null,"headnotes":null,"proceduralHistory":null,"attorneys":null,"natureOfSuit":"","citationCount":0,"judges":"","jurisdictionType":"","opinions":[{"id":9332142,"type":"majority","typeCode":"020lead","perCuriam":false,"author":"","joinedBy":"","pageCount":null,"textLength":0,"text":null}],"citations":[]}