{"id":9337830,"docketId":66647842,"caseName":"Lewis v. Pa. Higher Educ. Assistance Agency","caseNameFull":"Michael Thomas LEWIS v. PENNSYLVANIA HIGHER EDUCATION ASSISTANCE AGENCY","slug":"lewis-v-pa-higher-educ-assistance-agency","docketNumber":"17-1696","dateFiled":"2018-10-01","dateArgued":null,"dateCertGranted":null,"year":2018,"scdbId":"","direction":"","votesMajority":null,"votesMinority":null,"disposition":"","posture":"","syllabus":null,"summary":null,"headnotes":null,"proceduralHistory":null,"attorneys":null,"natureOfSuit":"","citationCount":0,"judges":"","jurisdictionType":"","opinions":[{"id":9333168,"type":"majority","typeCode":"020lead","perCuriam":false,"author":"","joinedBy":"","pageCount":null,"textLength":0,"text":null}],"citations":[]}