{"id":9338795,"docketId":66648850,"caseName":"Accord Healthcare, Inc. v. UCB, Inc.","caseNameFull":"ACCORD HEALTHCARE, INC. v. UCB, INC.","slug":"accord-healthcare-inc-v-ucb-inc","docketNumber":"18-441","dateFiled":"2018-11-19","dateArgued":null,"dateCertGranted":null,"year":2018,"scdbId":"","direction":"","votesMajority":null,"votesMinority":null,"disposition":"","posture":"","syllabus":null,"summary":null,"headnotes":null,"proceduralHistory":null,"attorneys":null,"natureOfSuit":"","citationCount":4,"judges":"","jurisdictionType":"","opinions":[{"id":9334133,"type":"majority","typeCode":"020lead","perCuriam":false,"author":"","joinedBy":"","pageCount":null,"textLength":0,"text":null}],"citations":[]}