{"id":9346106,"docketId":66658983,"caseName":"Alvis v. Schilling","caseNameFull":"James Michael ALVIS v. Leland W. SCHILLING.","slug":"alvis-v-schilling","docketNumber":"18-665","dateFiled":"2019-01-22","dateArgued":null,"dateCertGranted":null,"year":2019,"scdbId":"","direction":"","votesMajority":null,"votesMinority":null,"disposition":"","posture":"","syllabus":null,"summary":null,"headnotes":null,"proceduralHistory":null,"attorneys":null,"natureOfSuit":"","citationCount":0,"judges":"","jurisdictionType":"","opinions":[{"id":9341553,"type":"majority","typeCode":"020lead","perCuriam":false,"author":"","joinedBy":"","pageCount":null,"textLength":0,"text":null}],"citations":[]}