{"id":9347567,"docketId":66660630,"caseName":"Law v. Siegel","caseNameFull":"Stephen LAW v. Alfred H. SIEGEL, Chapter 7 Trustee.","slug":"law-v-siegel","docketNumber":"No. 12\u20135196.","dateFiled":"2013-11-18","dateArgued":null,"dateCertGranted":null,"year":2013,"scdbId":"","direction":"","votesMajority":null,"votesMinority":null,"disposition":"","posture":"","syllabus":null,"summary":null,"headnotes":null,"proceduralHistory":null,"attorneys":null,"natureOfSuit":"","citationCount":0,"judges":"","jurisdictionType":"","opinions":[{"id":9343023,"type":"majority","typeCode":"020lead","perCuriam":false,"author":"","joinedBy":"","pageCount":null,"textLength":0,"text":null}],"citations":[]}