{"id":9347818,"docketId":66660994,"caseName":"Tarrant Reg'l Water Dist. v. Herrmann","caseNameFull":"TARRANT REGIONAL WATER DISTRICT v. Rudolf John HERRMANN","slug":"tarrant-regl-water-dist-v-herrmann","docketNumber":"No. 11\u2013889.","dateFiled":"2013-04-12","dateArgued":null,"dateCertGranted":null,"year":2013,"scdbId":"","direction":"","votesMajority":null,"votesMinority":null,"disposition":"","posture":"","syllabus":null,"summary":null,"headnotes":null,"proceduralHistory":null,"attorneys":null,"natureOfSuit":"","citationCount":0,"judges":"","jurisdictionType":"","opinions":[{"id":9343274,"type":"majority","typeCode":"020lead","perCuriam":false,"author":"","joinedBy":"","pageCount":null,"textLength":0,"text":null}],"citations":[]}