{"id":9347777,"docketId":66660939,"caseName":"Jackson-Forsythe v. United States","caseNameFull":"Hope JACKSON-FORSYTHE and Edwardo M. Forsythe v. UNITED STATES.","slug":"jackson-forsythe-v-united-states","docketNumber":"12-9037","dateFiled":"2013-04-01","dateArgued":null,"dateCertGranted":null,"year":2013,"scdbId":"","direction":"","votesMajority":null,"votesMinority":null,"disposition":"","posture":"","syllabus":null,"summary":null,"headnotes":null,"proceduralHistory":null,"attorneys":null,"natureOfSuit":"","citationCount":0,"judges":"","jurisdictionType":"","opinions":[{"id":9343233,"type":"majority","typeCode":"020lead","perCuriam":false,"author":"","joinedBy":"","pageCount":null,"textLength":0,"text":null}],"citations":[]}