{"id":9348879,"docketId":66662102,"caseName":"Standing Joint Legislative Comm. on Reapportionment of Miss. Legislature v. Miss. State Conference of the Nat'l Ass'n for the Advancement of Colored People","caseNameFull":"The STANDING JOINT LEGISLATIVE COMMITTEE ON REAPPORTIONMENT OF the MISSISSIPPI LEGISLATURE v. MISSISSIPPI STATE CONFERENCE OF the NATIONAL ASSOCIATION FOR THE ADVANCEMENT OF COLORED PEOPLE","slug":"standing-joint-legislative-comm-on-reapportionment-of-miss-legislature-v-miss-st","docketNumber":"12-1132","dateFiled":"2013-05-20","dateArgued":null,"dateCertGranted":null,"year":2013,"scdbId":"","direction":"","votesMajority":null,"votesMinority":null,"disposition":"","posture":"","syllabus":null,"summary":null,"headnotes":null,"proceduralHistory":null,"attorneys":null,"natureOfSuit":"","citationCount":0,"judges":"","jurisdictionType":"","opinions":[{"id":9344335,"type":"majority","typeCode":"020lead","perCuriam":false,"author":"","joinedBy":"","pageCount":null,"textLength":0,"text":null}],"citations":[]}