{"id":9349494,"docketId":66662766,"caseName":"Pietri v. Crews","caseNameFull":"Elliot PIETRI v. Michael D. CREWS, Secretary, Florida Department of Corrections","slug":"pietri-v-crews","docketNumber":"12-10057","dateFiled":"2013-06-10","dateArgued":null,"dateCertGranted":null,"year":2013,"scdbId":"","direction":"","votesMajority":null,"votesMinority":null,"disposition":"","posture":"","syllabus":null,"summary":null,"headnotes":null,"proceduralHistory":null,"attorneys":null,"natureOfSuit":"","citationCount":0,"judges":"","jurisdictionType":"","opinions":[{"id":9344950,"type":"majority","typeCode":"020lead","perCuriam":false,"author":"","joinedBy":"","pageCount":null,"textLength":0,"text":null}],"citations":[]}