{"id":9349256,"docketId":66662512,"caseName":"Isaacson v. Berrigan","caseNameFull":"Eugene E. ISAACSON v. Shawn BERRIGAN","slug":"isaacson-v-berrigan","docketNumber":"No. 12\u20138783.","dateFiled":"2013-06-03","dateArgued":null,"dateCertGranted":null,"year":2013,"scdbId":"","direction":"","votesMajority":null,"votesMinority":null,"disposition":"","posture":"","syllabus":null,"summary":null,"headnotes":null,"proceduralHistory":null,"attorneys":null,"natureOfSuit":"","citationCount":0,"judges":"","jurisdictionType":"","opinions":[{"id":9344712,"type":"majority","typeCode":"020lead","perCuriam":false,"author":"","joinedBy":"","pageCount":null,"textLength":0,"text":null}],"citations":[]}