{"id":9350481,"docketId":66663852,"caseName":"Carwie ex rel. Harris v. Knudsen","caseNameFull":"J. Gregory CARWIE, Conservator on Behalf of Emil Harris v. PETER KNUDSEN, A/S.","slug":"carwie-ex-rel-harris-v-knudsen","docketNumber":"12-1232","dateFiled":"2013-06-17","dateArgued":null,"dateCertGranted":null,"year":2013,"scdbId":"","direction":"","votesMajority":null,"votesMinority":null,"disposition":"","posture":"","syllabus":null,"summary":null,"headnotes":null,"proceduralHistory":null,"attorneys":null,"natureOfSuit":"","citationCount":0,"judges":"","jurisdictionType":"","opinions":[{"id":9345949,"type":"majority","typeCode":"020lead","perCuriam":false,"author":"","joinedBy":"","pageCount":null,"textLength":0,"text":null}],"citations":[]}