{"id":9359853,"docketId":66721214,"caseName":"Bradley v. Davis","caseNameFull":"Meria James BRADLEY v. Lorie DAVIS, Director, Texas Department of Criminal Justice, Correctional Institutions Division.","slug":"bradley-v-davis","docketNumber":"No. 18\u20137867.","dateFiled":"2019-04-15","dateArgued":null,"dateCertGranted":null,"year":2019,"scdbId":"","direction":"","votesMajority":null,"votesMinority":null,"disposition":"","posture":"","syllabus":null,"summary":null,"headnotes":null,"proceduralHistory":null,"attorneys":null,"natureOfSuit":"","citationCount":0,"judges":"","jurisdictionType":"","opinions":[{"id":9355329,"type":"majority","typeCode":"020lead","perCuriam":false,"author":"","joinedBy":"","pageCount":null,"textLength":0,"text":null}],"citations":[]}