{"id":9359345,"docketId":66720706,"caseName":"Alfetlawi v. Klee","caseNameFull":"Rahim ALFETLAWI v. Paul KLEE, Warden.","slug":"alfetlawi-v-klee","docketNumber":"No. 18M112.","dateFiled":"2019-03-18","dateArgued":null,"dateCertGranted":null,"year":2019,"scdbId":"","direction":"","votesMajority":null,"votesMinority":null,"disposition":"","posture":"","syllabus":null,"summary":null,"headnotes":null,"proceduralHistory":null,"attorneys":null,"natureOfSuit":"","citationCount":0,"judges":"","jurisdictionType":"","opinions":[{"id":9354821,"type":"majority","typeCode":"020lead","perCuriam":false,"author":"","joinedBy":"","pageCount":null,"textLength":0,"text":null}],"citations":[]}