{"id":9359332,"docketId":66720693,"caseName":"Blanton v. Clarke","caseNameFull":"Stephen BLANTON v. Harold W. CLARKE, Director, Virginia Department of Corrections.","slug":"blanton-v-clarke","docketNumber":"18-7954","dateFiled":"2019-03-18","dateArgued":null,"dateCertGranted":null,"year":2019,"scdbId":"","direction":"","votesMajority":null,"votesMinority":null,"disposition":"","posture":"","syllabus":null,"summary":null,"headnotes":null,"proceduralHistory":null,"attorneys":null,"natureOfSuit":"","citationCount":0,"judges":"","jurisdictionType":"","opinions":[{"id":9354808,"type":"majority","typeCode":"020lead","perCuriam":false,"author":"","joinedBy":"","pageCount":null,"textLength":0,"text":null}],"citations":[]}