{"id":9359453,"docketId":66720814,"caseName":"Haynesworth v. S.C. Dep't of Mental Health","caseNameFull":"Alphonso HAYNESWORTH v. SOUTH CAROLINA DEPARTMENT OF MENTAL HEALTH","slug":"haynesworth-v-sc-dept-of-mental-health","docketNumber":"18-7728","dateFiled":"2019-03-25","dateArgued":null,"dateCertGranted":null,"year":2019,"scdbId":"","direction":"","votesMajority":null,"votesMinority":null,"disposition":"","posture":"","syllabus":null,"summary":null,"headnotes":null,"proceduralHistory":null,"attorneys":null,"natureOfSuit":"","citationCount":0,"judges":"","jurisdictionType":"","opinions":[{"id":9354929,"type":"majority","typeCode":"020lead","perCuriam":false,"author":"","joinedBy":"","pageCount":null,"textLength":0,"text":null}],"citations":[]}