{"id":9359906,"docketId":66721267,"caseName":"Fykes v. West Virginia","caseNameFull":"William FYKES v. WEST VIRGINIA.","slug":"fykes-v-west-virginia","docketNumber":"18-8001","dateFiled":"2019-04-15","dateArgued":null,"dateCertGranted":null,"year":2019,"scdbId":"","direction":"","votesMajority":null,"votesMinority":null,"disposition":"","posture":"","syllabus":null,"summary":null,"headnotes":null,"proceduralHistory":null,"attorneys":null,"natureOfSuit":"","citationCount":0,"judges":"","jurisdictionType":"","opinions":[{"id":9355382,"type":"majority","typeCode":"020lead","perCuriam":false,"author":"","joinedBy":"","pageCount":null,"textLength":0,"text":null}],"citations":[]}