{"id":9360300,"docketId":66721661,"caseName":"Dilts v. Michgan","caseNameFull":"Wayland Lynn DILTS v. MICHIGAN.","slug":"dilts-v-michgan","docketNumber":"18-8207","dateFiled":"2019-04-29","dateArgued":null,"dateCertGranted":null,"year":2019,"scdbId":"","direction":"","votesMajority":null,"votesMinority":null,"disposition":"","posture":"","syllabus":null,"summary":null,"headnotes":null,"proceduralHistory":null,"attorneys":null,"natureOfSuit":"","citationCount":0,"judges":"","jurisdictionType":"","opinions":[{"id":9355776,"type":"majority","typeCode":"020lead","perCuriam":false,"author":"","joinedBy":"","pageCount":null,"textLength":0,"text":null}],"citations":[]}