{"id":9360672,"docketId":66722033,"caseName":"Kulick v. Leisure Vill. Ass'n, Inc.","caseNameFull":"Robert J. KULICK v. LEISURE VILLAGE ASSOCIATION, INC.","slug":"kulick-v-leisure-vill-assn-inc","docketNumber":"No. 18\u20136907.","dateFiled":"2019-05-20","dateArgued":null,"dateCertGranted":null,"year":2019,"scdbId":"","direction":"","votesMajority":null,"votesMinority":null,"disposition":"","posture":"","syllabus":null,"summary":null,"headnotes":null,"proceduralHistory":null,"attorneys":null,"natureOfSuit":"","citationCount":0,"judges":"","jurisdictionType":"","opinions":[{"id":9356148,"type":"majority","typeCode":"020lead","perCuriam":false,"author":"","joinedBy":"","pageCount":null,"textLength":0,"text":null}],"citations":[]}