{"id":9360289,"docketId":66721650,"caseName":"Lucy v. Dialysis Assocs.","caseNameFull":"William N. LUCY, Personal Representative of Annie D. Fox v. DIALYSIS ASSOCIATES","slug":"lucy-v-dialysis-assocs","docketNumber":"No. 18\u20138180.","dateFiled":"2019-04-29","dateArgued":null,"dateCertGranted":null,"year":2019,"scdbId":"","direction":"","votesMajority":null,"votesMinority":null,"disposition":"","posture":"","syllabus":null,"summary":null,"headnotes":null,"proceduralHistory":null,"attorneys":null,"natureOfSuit":"","citationCount":0,"judges":"","jurisdictionType":"","opinions":[{"id":9355765,"type":"majority","typeCode":"020lead","perCuriam":false,"author":"","joinedBy":"","pageCount":null,"textLength":0,"text":null}],"citations":[]}