{"id":9361356,"docketId":66722736,"caseName":"Horrell v. Downey","caseNameFull":"Phillip L. HORRELL v. Michael D. DOWNEY, Sheriff, Kankakee County, Illinois.","slug":"horrell-v-downey","docketNumber":"18-9163","dateFiled":"2019-06-17","dateArgued":null,"dateCertGranted":null,"year":2019,"scdbId":"","direction":"","votesMajority":null,"votesMinority":null,"disposition":"","posture":"","syllabus":null,"summary":null,"headnotes":null,"proceduralHistory":null,"attorneys":null,"natureOfSuit":"","citationCount":0,"judges":"","jurisdictionType":"","opinions":[{"id":9356832,"type":"majority","typeCode":"020lead","perCuriam":false,"author":"","joinedBy":"","pageCount":null,"textLength":0,"text":null}],"citations":[]}