{"id":9363026,"docketId":66724408,"caseName":"Shields v. Klein","caseNameFull":"Antonia SHIELDS v. Juda KLEIN.","slug":"shields-v-klein","docketNumber":"18-9389","dateFiled":"2019-10-07","dateArgued":null,"dateCertGranted":null,"year":2019,"scdbId":"","direction":"","votesMajority":null,"votesMinority":null,"disposition":"","posture":"","syllabus":null,"summary":null,"headnotes":null,"proceduralHistory":null,"attorneys":null,"natureOfSuit":"","citationCount":0,"judges":"","jurisdictionType":"","opinions":[{"id":9358502,"type":"majority","typeCode":"020lead","perCuriam":false,"author":"","joinedBy":"","pageCount":null,"textLength":0,"text":null}],"citations":[]}