{"id":9363936,"docketId":66725318,"caseName":"Lee v. United States","caseNameFull":"Darren L. LEE v. UNITED STATES","slug":"lee-v-united-states","docketNumber":"19-5085","dateFiled":"2019-11-18","dateArgued":null,"dateCertGranted":null,"year":2019,"scdbId":"","direction":"","votesMajority":null,"votesMinority":null,"disposition":"","posture":"","syllabus":null,"summary":null,"headnotes":null,"proceduralHistory":null,"attorneys":null,"natureOfSuit":"","citationCount":0,"judges":"","jurisdictionType":"","opinions":[{"id":9359412,"type":"majority","typeCode":"020lead","perCuriam":false,"author":"","joinedBy":"","pageCount":null,"textLength":0,"text":null}],"citations":[]}