{"id":9363722,"docketId":66725104,"caseName":"Buncich v. United States","caseNameFull":"John BUNCICH v. UNITED STATES.","slug":"buncich-v-united-states","docketNumber":"19-456","dateFiled":"2019-11-12","dateArgued":null,"dateCertGranted":null,"year":2019,"scdbId":"","direction":"","votesMajority":null,"votesMinority":null,"disposition":"","posture":"","syllabus":null,"summary":null,"headnotes":null,"proceduralHistory":null,"attorneys":null,"natureOfSuit":"","citationCount":0,"judges":"","jurisdictionType":"","opinions":[{"id":9359198,"type":"majority","typeCode":"020lead","perCuriam":false,"author":"","joinedBy":"","pageCount":null,"textLength":0,"text":null}],"citations":[]}