{"id":9366179,"docketId":66727561,"caseName":"Simpson v. Bishop","caseNameFull":"James Henry SIMPSON v. Martesha BISHOP","slug":"simpson-v-bishop","docketNumber":"19-7536","dateFiled":"2020-03-23","dateArgued":null,"dateCertGranted":null,"year":2020,"scdbId":"","direction":"","votesMajority":null,"votesMinority":null,"disposition":"","posture":"","syllabus":null,"summary":null,"headnotes":null,"proceduralHistory":null,"attorneys":null,"natureOfSuit":"","citationCount":0,"judges":"","jurisdictionType":"","opinions":[{"id":9361655,"type":"majority","typeCode":"020lead","perCuriam":false,"author":"","joinedBy":"","pageCount":null,"textLength":0,"text":null}],"citations":[]}