{"id":9366669,"docketId":66728055,"caseName":"Runnels v. Texas","caseNameFull":"William A. RUNNELS v. TEXAS.","slug":"runnels-v-texas","docketNumber":"19-7746","dateFiled":"2020-04-20","dateArgued":null,"dateCertGranted":null,"year":2020,"scdbId":"","direction":"","votesMajority":null,"votesMinority":null,"disposition":"","posture":"","syllabus":null,"summary":null,"headnotes":null,"proceduralHistory":null,"attorneys":null,"natureOfSuit":"","citationCount":0,"judges":"","jurisdictionType":"","opinions":[{"id":9362145,"type":"majority","typeCode":"020lead","perCuriam":false,"author":"","joinedBy":"","pageCount":null,"textLength":0,"text":null}],"citations":[]}